polyeval/__init__.py
polyeval/evaluation.py
polyeval/config/__init__.py
polyeval/config/model_config.py
polyeval/evaluators/__init__.py
polyeval/evaluators/answer_relevancy.py
polyeval/evaluators/context_precision.py
polyeval/evaluators/context_recall.py
polyeval/evaluators/custom_yaml.py
polyeval/evaluators/embedding_distance.py
polyeval/evaluators/faithfulness.py
polyeval/evaluators/json.py
polyeval/evaluators/llm_similarity.py
polyeval/evaluators/matchness.py
polyeval/evaluators/regex.py
polyeval/evaluators/string_distance.py
polyeval/utils/__init__.py
polyeval/utils/classify_helpers.py
polyeval/utils/helpers.py
polyeval/utils/model.py
tests/__init__.py
tests/test_custom_yaml.py
tests/test_embedding_distance.py
tests/test_is_json.py
tests/test_json_match.py
tests/test_json_schema_match.py
tests/test_llm_similarity.py
tests/test_match.py
tests/test_rag.py
tests/test_regex.py
tests/test_string_distance.py
zeval/__init__.py
zeval/evaluation.py
zeval/config/__init__.py
zeval/config/model_config.py
zeval/evaluators/__init__.py
zeval/evaluators/answer_relevancy.py
zeval/evaluators/context_precision.py
zeval/evaluators/context_recall.py
zeval/evaluators/faithfulness.py
zeval/evaluators/json.py
zeval/evaluators/matchness.py
zeval/utils/__init__.py
zeval/utils/helpers.py
zeval/utils/model.py
zeval/utils/model_caller.py
polyeval-0.1.0.dist-info/METADATA
polyeval-0.1.0.dist-info/WHEEL
polyeval-0.1.0.dist-info/top_level.txt
polyeval-0.1.0.dist-info/RECORD
