Metadata-Version: 2.1
Name: polyeval
Version: 0.1.0
Summary: A Python library for evaluating RAG outputs of Chinese large language models.
Home-page: https://github.com/evalsone/polyeval
Author: everfly
Author-email: tagriver@gmail.com
Classifier: Development Status :: 3 - Alpha
Classifier: Intended Audience :: Developers
Classifier: Programming Language :: Python :: 3
Classifier: Programming Language :: Python :: 3.7
Classifier: Programming Language :: Python :: 3.8
Classifier: Programming Language :: Python :: 3.9
Requires-Python: >=3.7
Requires-Dist: datasets
Requires-Dist: openai
Requires-Dist: unionllm
Requires-Dist: jsonschema
Requires-Dist: langchain
Requires-Dist: langchain-community
